agvtool_port/__init__.py
agvtool_port/__main__.py
agvtool_port-0.0.4.dist-info/METADATA
agvtool_port-0.0.4.dist-info/WHEEL
agvtool_port-0.0.4.dist-info/entry_points.txt
agvtool_port-0.0.4.dist-info/top_level.txt
agvtool_port-0.0.4.dist-info/RECORD
